odoo/addons/pos_payment_method_cashdro/README.rst
odoo/addons/pos_payment_method_cashdro/__init__.py
odoo/addons/pos_payment_method_cashdro/__manifest__.py
odoo/addons/pos_payment_method_cashdro/i18n/pos_payment_method_cashdro.pot
odoo/addons/pos_payment_method_cashdro/models/__init__.py
odoo/addons/pos_payment_method_cashdro/models/account_journal.py
odoo/addons/pos_payment_method_cashdro/readme/CONFIGURE.rst
odoo/addons/pos_payment_method_cashdro/readme/CONTRIBUTORS.rst
odoo/addons/pos_payment_method_cashdro/readme/DESCRIPTION.rst
odoo/addons/pos_payment_method_cashdro/readme/ROADMAP.rst
odoo/addons/pos_payment_method_cashdro/readme/USAGE.rst
odoo/addons/pos_payment_method_cashdro/static/description/icon.png
odoo/addons/pos_payment_method_cashdro/static/description/index.html
odoo/addons/pos_payment_method_cashdro/static/description/logo.png
odoo/addons/pos_payment_method_cashdro/static/src/js/models.js
odoo/addons/pos_payment_method_cashdro/static/src/js/screens.js
odoo/addons/pos_payment_method_cashdro/static/src/scss/pos_cashdro_terminal.scss
odoo/addons/pos_payment_method_cashdro/static/src/xml/pos_cashdro_terminal.xml
odoo/addons/pos_payment_method_cashdro/views/account_journal.xml
odoo/addons/pos_payment_method_cashdro/views/assets.xml
odoo12_addon_pos_payment_method_cashdro-12.0.1.0.1.dist-info/METADATA
odoo12_addon_pos_payment_method_cashdro-12.0.1.0.1.dist-info/WHEEL
odoo12_addon_pos_payment_method_cashdro-12.0.1.0.1.dist-info/top_level.txt
odoo12_addon_pos_payment_method_cashdro-12.0.1.0.1.dist-info/RECORD
